README.txt
setup.py
nose_perfdump.egg-info/PKG-INFO
nose_perfdump.egg-info/SOURCES.txt
nose_perfdump.egg-info/dependency_links.txt
nose_perfdump.egg-info/entry_points.txt
nose_perfdump.egg-info/requires.txt
nose_perfdump.egg-info/top_level.txt
perfdump/__init__.py
perfdump/connection.py
perfdump/console.py
perfdump/html.py
perfdump/models.py
perfdump/plugin.py