Metadata-Version: 1.0
Name: nose-perfdump
Version: 1.5
Summary: Dump per-test performance metrics to an SQLite database for querying.
Home-page: https://github.com/etscrivner/nose-perfdump
Author: Eric Scrivner
Author-email: eric.t.scrivner@gmail.com
License: BSD
Keywords: nose,nose plugin,profiler,profiling,tests,unittest
Platform: UNKNOWN
